abiftool.py
fetchmgr.py
abiflib/__init__.py
abiflib/abifregex.py
abiflib/approval_tally.py
abiflib/core.py
abiflib/debtally.py
abiflib/debvote_fmt.py
abiflib/devtools.py
abiflib/fptp_tally.py
abiflib/html_output.py
abiflib/html_output_common.py
abiflib/html_output_pairwise.py
abiflib/html_output_scorestar.py
abiflib/irv_tally.py
abiflib/irvtally.py
abiflib/nameq.py
abiflib/nameq_fmt.py
abiflib/nycdem_fmt.py
abiflib/pairwise.py
abiflib/pairwise_tally.py
abiflib/preflib.py
abiflib/preflib_fmt.py
abiflib/score_star_tally.py
abiflib/scorestar.py
abiflib/sfjson_fmt.py
abiflib/sftxt.py
abiflib/sftxt_fmt.py
abiflib/stlcvr_fmt.py
abiflib/text_output.py
abiflib/textoutput.py
abiflib/transform_core.py
abiflib/util.py
abiflib/vizelect.py
abiflib/vizelect_output.py
abiflib/widj_fmt.py
abiflib/widjfuncs.py
abiflib/__pycache__/__init__.cpython-312.pyc
abiflib/__pycache__/__init__.cpython-313.pyc
abiflib/__pycache__/abifregex.cpython-312.pyc
abiflib/__pycache__/abifregex.cpython-313.pyc
abiflib/__pycache__/approval_tally.cpython-313.pyc
abiflib/__pycache__/core.cpython-312.pyc
abiflib/__pycache__/core.cpython-313.pyc
abiflib/__pycache__/debvote_fmt.cpython-312.pyc
abiflib/__pycache__/debvote_fmt.cpython-313.pyc
abiflib/__pycache__/devtools.cpython-312.pyc
abiflib/__pycache__/devtools.cpython-313.pyc
abiflib/__pycache__/fptp_tally.cpython-312.pyc
abiflib/__pycache__/fptp_tally.cpython-313.pyc
abiflib/__pycache__/html_output.cpython-312.pyc
abiflib/__pycache__/html_output.cpython-313.pyc
abiflib/__pycache__/html_output_common.cpython-312.pyc
abiflib/__pycache__/html_output_common.cpython-313.pyc
abiflib/__pycache__/html_output_pairwise.cpython-312.pyc
abiflib/__pycache__/html_output_pairwise.cpython-313.pyc
abiflib/__pycache__/html_output_scorestar.cpython-312.pyc
abiflib/__pycache__/html_output_scorestar.cpython-313.pyc
abiflib/__pycache__/irv_tally.cpython-312.pyc
abiflib/__pycache__/irv_tally.cpython-313.pyc
abiflib/__pycache__/nameq_fmt.cpython-312.pyc
abiftool-0.34.0.dist-info/licenses/LICENSE
abiftool-0.34.0.dist-info/METADATA
abiftool-0.34.0.dist-info/WHEEL
abiftool-0.34.0.dist-info/entry_points.txt
abiftool-0.34.0.dist-info/top_level.txt
abiftool-0.34.0.dist-info/RECORD
