Metadata-Version: 2.4
Name: abiftool
Version: 0.34.0
Summary: abiftool parses, converts and analyzes ABIF (Aggregated Ballot Information Format) files.
Author-email: Rob Lanphier <robla@robla.net>
License: GPL-3.0
Classifier: Programming Language :: Python :: 3
Classifier: License :: OSI Approved :: GNU General Public License v3 or later (GPLv3+)
Classifier: Operating System :: OS Independent
Classifier: Intended Audience :: Science/Research
Classifier: Topic :: Sociology :: History
Requires-Python: >=3.8
License-File: LICENSE
Requires-Dist: BeautifulSoup4
Requires-Dist: graphviz
Requires-Dist: openpyxl
Requires-Dist: pandas
Requires-Dist: requests
Requires-Dist: Texttable
Dynamic: license-file
